AUTHORS.rst
CHANGES.rst
LICENSE
MANIFEST.in
README.rst
package.json
setup.py
matrix_angular_sdk.egg-info/PKG-INFO
matrix_angular_sdk.egg-info/SOURCES.txt
matrix_angular_sdk.egg-info/dependency_links.txt
matrix_angular_sdk.egg-info/not-zip-safe
matrix_angular_sdk.egg-info/top_level.txt
syweb/__init__.py
syweb/webclient/README
syweb/webclient/VERSION
syweb/webclient/config.sample.js
syweb/webclient/favicon.ico
syweb/webclient/index.html
syweb/webclient/app/app-controller.js
syweb/webclient/app/app-directive.js
syweb/webclient/app/app-filter.js
syweb/webclient/app/app.css
syweb/webclient/app/app.js
syweb/webclient/app/bootstrap.css
syweb/webclient/app/mobile.css
syweb/webclient/app/components/dialogs/dialog-service.js
syweb/webclient/app/components/fileInput/file-input-directive.js
syweb/webclient/app/components/fileUpload/file-upload-service.js
syweb/webclient/app/components/matrix/commands-service.js
syweb/webclient/app/components/matrix/event-handler-service.js
syweb/webclient/app/components/matrix/event-reaper-service.js
syweb/webclient/app/components/matrix/event-stream-service.js
syweb/webclient/app/components/matrix/matrix-call.js
syweb/webclient/app/components/matrix/matrix-filter.js
syweb/webclient/app/components/matrix/matrix-phone-service.js
syweb/webclient/app/components/matrix/matrix-service.js
syweb/webclient/app/components/matrix/model-service.js
syweb/webclient/app/components/matrix/notification-service.js
syweb/webclient/app/components/matrix/presence-service.js
syweb/webclient/app/components/matrix/recents-service.js
syweb/webclient/app/components/matrix/typing-service.js
syweb/webclient/app/components/matrix/version-service.js
syweb/webclient/app/components/matrix/webrtc-service.js
syweb/webclient/app/components/utilities/utilities-service.js
syweb/webclient/app/home/home-controller.js
syweb/webclient/app/home/home.html
syweb/webclient/app/login/login-controller.js
syweb/webclient/app/login/login.html
syweb/webclient/app/login/register-controller.js
syweb/webclient/app/login/register.html
syweb/webclient/app/login/reset-password-controller.js
syweb/webclient/app/login/reset-password.html
syweb/webclient/app/payment/payment-controller.js
