Metadata-Version: 1.0
Name: matrix-angular-sdk
Version: 0.6.8
Summary: Matrix Angular Sdk
Home-page: UNKNOWN
Author: UNKNOWN
Author-email: UNKNOWN
License: UNKNOWN
Platform: UNKNOWN
